openedx_webhooks/__init__.py
openedx_webhooks/admin.py
openedx_webhooks/apps.py
openedx_webhooks/filters.py
openedx_webhooks/models.py
openedx_webhooks/receivers.py
openedx_webhooks/urls.py
openedx_webhooks/utils.py
openedx_webhooks/migrations/0001_initial.py
openedx_webhooks/migrations/0002_webfilter.py
openedx_webhooks/migrations/0003_auto_20230607_1246.py
openedx_webhooks/migrations/0004_auto_20230613_1033.py
openedx_webhooks/migrations/0005_alter_webfilter_event.py
openedx_webhooks/migrations/0006_alter_webfilter_event.py
openedx_webhooks/migrations/0007_alter_webfilter_event.py
openedx_webhooks/migrations/__init__.py
openedx_webhooks/settings/__init__.py
openedx_webhooks/settings/common.py
openedx_webhooks-19.0.1.dist-info/licenses/LICENSE.txt
test_utils/__init__.py
openedx_webhooks-19.0.1.dist-info/METADATA
openedx_webhooks-19.0.1.dist-info/WHEEL
openedx_webhooks-19.0.1.dist-info/entry_points.txt
openedx_webhooks-19.0.1.dist-info/top_level.txt
openedx_webhooks-19.0.1.dist-info/RECORD
