Metadata-Version: 2.4
Name: openedx_webhooks
Version: 19.0.1
Summary: Webhooks for Open edX
Home-page: https://github.com/aulasneo/openedx-webhooks
Author: Aulasneo
Author-email: andres@aulasneo.com
License: AGPL 3.0
Keywords: Openedx webhooks
Classifier: Development Status :: 3 - Alpha
Classifier: Framework :: Django
Classifier: Framework :: Django :: 3.2
Classifier: Intended Audience :: Developers
Classifier: License :: OSI Approved :: GNU Affero General Public License v3 or later (AGPLv3+)
Classifier: Natural Language :: English
Classifier: Programming Language :: Python :: 3
Classifier: Programming Language :: Python :: 3.8
Requires-Python: >=3.8
License-File: LICENSE.txt
Requires-Dist: Django
Requires-Dist: attrs
Requires-Dist: django-model-utils
Requires-Dist: edx-sphinx-theme
Requires-Dist: edx_opaque_keys
Requires-Dist: openedx-filters
Requires-Dist: requests
Requires-Dist: xblock
Dynamic: author
Dynamic: author-email
Dynamic: classifier
Dynamic: description
Dynamic: description-content-type
Dynamic: home-page
Dynamic: keywords
Dynamic: license
Dynamic: license-file
Dynamic: requires-dist
Dynamic: requires-python
Dynamic: summary
